kamera/__init__.py
kamera/app.py
kamera/camera.py
kamera/settings.py
kamera/static/styles.css
kamera/templates/index.html
kamera-0.4.2.dist-info/LICENSE
kamera-0.4.2.dist-info/METADATA
kamera-0.4.2.dist-info/WHEEL
kamera-0.4.2.dist-info/entry_points.txt
kamera-0.4.2.dist-info/top_level.txt
kamera-0.4.2.dist-info/RECORD
